pyansistring/__init__.py
pyansistring/arts.py
pyansistring/constants.py
pyansistring/helpers.py
pyansistring/pyansistring.py
pyansistring-0.0.2.dist-info/METADATA
pyansistring-0.0.2.dist-info/WHEEL
pyansistring-0.0.2.dist-info/licenses/LICENSE
pyansistring-0.0.2.dist-info/RECORD
