Metadata-Version: 2.3
Name: pyansistring
Version: 0.0.2
Summary: A small library for fast color styling of the string using ANSI escape sequences.
Project-URL: Repository, https://github.com/l1asis/pyansistring.git
Project-URL: Issues, https://github.com/l1asis/pyansistring/issues
Author: Volodymyr Horshenin
License: MIT License
License-File: LICENSE
Keywords: ANSI escape sequences,colored string,colored text,colors,terminal
Classifier: Development Status :: 3 - Alpha
Classifier: Intended Audience :: Other Audience
Classifier: License :: OSI Approved :: MIT License
Classifier: Operating System :: OS Independent
Classifier: Programming Language :: Python :: 3
Classifier: Topic :: Terminals
Classifier: Topic :: Text Processing
Requires-Python: >=3.10
